oresat_gps/__init__.py
oresat_gps/__main__.py
oresat_gps/_version.py
oresat_gps/gps_service.py
oresat_gps/skytraq.py
oresat_gps/templates/skytraq.html
oresat_gps-1.4.0.dist-info/LICENSE
oresat_gps-1.4.0.dist-info/METADATA
oresat_gps-1.4.0.dist-info/WHEEL
oresat_gps-1.4.0.dist-info/entry_points.txt
oresat_gps-1.4.0.dist-info/top_level.txt
oresat_gps-1.4.0.dist-info/RECORD
